[{"id":1,"phones":["+375-(29)-765-70-63"],"lastName":"shestsiaryn","firstName":"yury","comment":"Me"},{"id":2,"phones":[],"lastName":"dfds","firstName":"fdsf","comment":"fd fd fd"},{"id":3,"phones":[],"lastName":"df","firstName":"fdf","comment":"dfds"},{"id":4,"phones":[],"lastName":"dsf","firstName":"sdf","comment":"sdfs"},{"id":5,"phones":[],"lastName":"ffdf","firstName":"fds","comment":"sdf f  w"},{"id":6,"phones":[],"lastName":"dfs","firstName":"fewf","comment":"fds fd df sdf"},{"id":7,"phones":[],"lastName":"dsf","firstName":"eeeeeeeeeeeeeeee","comment":"qweeeeeeeeeeeeeeeeeeeeeeeeeeee"}]